{
  "greeting": [
    "hola",
    "buen dia",
    "buenos dias",
    "buenas",
    "buenas tardes",
    "buenas noches",
    "saludos",
    "bendiciones",
    "klk",
    "que lo que",
    "hello",
    "hi"
  ],
  "catalog": [
    "que mercancia hay",
    "que mercancía hay",
    "que productos hay",
    "que venden",
    "que tienen",
    "que hay",
    "ver catalogo",
    "ver catálogo",
    "mandame catalogo",
    "mándame catálogo",
    "catalogo",
    "catálogo",
    "mercancia",
    "mercancía",
    "productos disponibles"
  ],
  "payment": [
    "como pago",
    "como puedo pagar",
    "donde pago",
    "cuenta",
    "banco",
    "transferencia",
    "deposito",
    "depósito",
    "datos bancarios",
    "metodo de pago",
    "método de pago",
    "quiero pagar"
  ],
  "location": [
    "donde estan",
    "donde están",
    "donde estan ubicados",
    "donde están ubicados",
    "ubicacion",
    "ubicación",
    "direccion",
    "dirección",
    "donde queda",
    "local",
    "tienda fisica",
    "tienda física",
    "sucursal"
  ],
  "hours": [
    "horario",
    "a que hora",
    "a qué hora",
    "estan abiertos",
    "están abiertos",
    "hora cierran",
    "hora abren",
    "abren hoy",
    "cierran hoy"
  ],
  "delivery": [
    "delivery",
    "envio",
    "envío",
    "entrega",
    "domicilio",
    "mandan",
    "llevan",
    "hacen delivery",
    "para enviar",
    "cuanto el envio",
    "cuánto el envío"
  ],
  "more": [
    "mas",
    "más",
    "tienen mas",
    "tienen más",
    "hay mas",
    "hay más",
    "otros",
    "otras",
    "otro modelo",
    "mas modelos",
    "más modelos",
    "mas opciones",
    "más opciones",
    "quiero ver mas",
    "quiero ver más"
  ],
  "photo": [
    "foto",
    "imagen",
    "dame foto",
    "mandame foto",
    "mándame foto",
    "quiero verla",
    "quiero verlo",
    "ensename",
    "enséñame",
    "ver foto"
  ],
  "wholesale": [
    "mayor",
    "por mayor",
    "al mayor",
    "precio mayor",
    "mayoreo",
    "docena",
    "por docena",
    "caja",
    "por caja",
    "cantidad"
  ],
  "change_product": [
    "otro producto",
    "otra cosa",
    "algo diferente",
    "no ese",
    "no quiero ese",
    "quiero otro",
    "otro modelo",
    "diferente",
    "otra mercancia",
    "otra mercancía"
  ],
  "yes": [
    "si",
    "sí",
    "ok",
    "okay",
    "dale",
    "claro",
    "perfecto",
    "lo quiero",
    "quiero ese",
    "me gusta",
    "separalo",
    "sepáralo"
  ]
}